GameOfLife/GameDriver.py
GameOfLife/GameOfLife.py
GameOfLife/__init__.py
GameOfLife/__main__.py
py_GameOfLife_simplified-0.0.0.2.dist-info/LICENSE
py_GameOfLife_simplified-0.0.0.2.dist-info/METADATA
py_GameOfLife_simplified-0.0.0.2.dist-info/WHEEL
py_GameOfLife_simplified-0.0.0.2.dist-info/top_level.txt
py_GameOfLife_simplified-0.0.0.2.dist-info/RECORD
