Metadata-Version: 2.1
Name: py-GameOfLife-simplified
Version: 0.0.0.2
Summary: A simple implementation of Conway's Game of Life
Home-page: https://github.com/avinashkarhana/GameOfLife
Author: Avinash Karhana
Author-email: avinashkarhana1@gmail.com
License: UNKNOWN
Keywords: GameOfLife,gameoflife,conwaysgame
Platform: UNKNOWN
Classifier: Programming Language :: Python :: 3
Classifier: Programming Language :: Python :: 3.6
Classifier: Programming Language :: Python :: 3.7
Classifier: Programming Language :: Python :: 3.8
Classifier: Programming Language :: Python :: 3.9
Classifier: Programming Language :: Python :: 3.10
Classifier: License :: OSI Approved :: MIT License
Classifier: Operating System :: OS Independent
Requires-Python: >=3.5
License-File: LICENSE
